oceanengine/__init__.py
oceanengine/ad.py
oceanengine/ad_postback.py
oceanengine/business.py
oceanengine/cc.py
oceanengine/e.py
oceanengine/m_toutiao.py
oceanengine/open.py
oceanengine-0.1.13.dist-info/METADATA
oceanengine-0.1.13.dist-info/WHEEL
oceanengine-0.1.13.dist-info/top_level.txt
oceanengine-0.1.13.dist-info/RECORD
