Metadata-Version: 2.1
Name: oceanengine
Version: 0.1.13
Summary: make it easy to use oceanengine
Home-page: https://gitee.com/ZeroSeeker/oceanengine
Author: ZeroSeeker
Author-email: zeroseeker@foxmail.com
Classifier: Programming Language :: Python :: 3
Classifier: License :: OSI Approved :: MIT License
Classifier: Operating System :: OS Independent
Requires-Dist: lazysdk (>=0.1.66)
